README.rst
setup.py
pypath_magic/__init__.py
pypath_magic/cli.py
pypath_magic/core.py
pypath_magic/ipymagic.py
pypath_magic/testing.py
pypath_magic/utils.py
pypath_magic.egg-info/PKG-INFO
pypath_magic.egg-info/SOURCES.txt
pypath_magic.egg-info/dependency_links.txt
pypath_magic.egg-info/entry_points.txt
pypath_magic.egg-info/requires.txt
pypath_magic.egg-info/top_level.txt