Metadata-Version: 1.1
Name: pypath-magic
Version: 0.3.1
Summary: IPython magic and CLI to manipulate the Python path
Home-page: http://tonysyu.github.com/pypath_magic
Author: Tony S. Yu
Author-email: tsyu80@gmail.com
License: Modified BSD
Download-URL: http://tonysyu.github.com/pypath_magic
Keywords: PYTHONPATH,utility,IPython
Platform: UNKNOWN
Classifier: Topic :: Utilities
Classifier: Framework :: IPython
Classifier: Intended Audience :: Developers
Classifier: Topic :: Desktop Environment :: File Managers
